Metadata-Version: 1.0
Name: icebreaker
Version: 0.2.0
Summary: Python API for the JBEI ICE sample manager.
Home-page: UNKNOWN
Author: Zulko
Author-email: UNKNOWN
License: see LICENSE.txt
Keywords: synthetic biology sample manager
Platform: UNKNOWN
